PyQtRPT/PyQtRPT.pyd
PyQtRPT/QtCore.pyd
PyQtRPT/QtCore4.dll
PyQtRPT/QtGui4.dll
PyQtRPT/QtRPTaps.dll
PyQtRPT/QtScript4.dll
PyQtRPT/QtSql4.dll
PyQtRPT/QtXml4.dll
PyQtRPT/QtZint.dll
PyQtRPT/__init__.py
PyQtRPT/gpl-3.0.txt
PyQtRPT/pyside-python3.4.dll
PyQtRPT/shiboken-python3.4.dll
PyQtRPT/examples/example1.py
PyQtRPT/examples/example10.py
PyQtRPT/examples/example11.py
PyQtRPT/examples/example12.py
PyQtRPT/examples/example13.py
PyQtRPT/examples/example14.py
PyQtRPT/examples/example15.py
PyQtRPT/examples/example16.py
PyQtRPT/examples/example17.py
PyQtRPT/examples/example18.py
PyQtRPT/examples/example1_Signal.py
PyQtRPT/examples/example2.py
PyQtRPT/examples/example2_Signal.py
PyQtRPT/examples/example3.py
PyQtRPT/examples/example4.py
PyQtRPT/examples/example4_Signal.py
PyQtRPT/examples/example5.py
PyQtRPT/examples/example5_Signal.py
PyQtRPT/examples/example6.py
PyQtRPT/examples/example6_2.py
PyQtRPT/examples/example6_Signal.py
PyQtRPT/examples/example7.py
PyQtRPT/examples/example8.py
PyQtRPT/examples/example8_Signal.py
PyQtRPT/examples/example9.py
PyQtRPT/examples/examples_report/RussianInvaders.xml
PyQtRPT/examples/examples_report/example.sqlite
PyQtRPT/examples/examples_report/example1.xml
PyQtRPT/examples/examples_report/example10.xml
PyQtRPT/examples/examples_report/example11.xml
PyQtRPT/examples/examples_report/example11_2.xml
PyQtRPT/examples/examples_report/example12.xml
PyQtRPT/examples/examples_report/example13.xml
PyQtRPT/examples/examples_report/example15.xml
PyQtRPT/examples/examples_report/example16.xml
PyQtRPT/examples/examples_report/example17.xml
PyQtRPT/examples/examples_report/example18.xml
PyQtRPT/examples/examples_report/example2.xml
PyQtRPT/examples/examples_report/example3.xml
PyQtRPT/examples/examples_report/example4.xml
PyQtRPT/examples/examples_report/example5.xml
PyQtRPT/examples/examples_report/example6a.xml
PyQtRPT/examples/examples_report/example6b.xml
PyQtRPT-1.5.5.dist-info/DESCRIPTION.rst
PyQtRPT-1.5.5.dist-info/METADATA
PyQtRPT-1.5.5.dist-info/RECORD
PyQtRPT-1.5.5.dist-info/WHEEL
PyQtRPT-1.5.5.dist-info/metadata.json
PyQtRPT-1.5.5.dist-info/top_level.txt
