Metadata-Version: 2.0
Name: PyQtRPT
Version: 1.5.5
Summary: PySide binding for QtRPT, QtRPT is the easy-to-use print report engine written in C++ QtToolkit.
Home-page: https://sourceforge.net/projects/pyqtrpt/
Author: numael garay
Author-email: numaelis@gmail.com
License: UNKNOWN
Keywords: pyside qtrpt shiboken
Platform: UNKNOWN
Classifier: Development Status :: 4 - Beta
Classifier: Environment :: X11 Applications :: Qt
Classifier: License :: OSI Approved :: GNU General Public License (GPL)
Classifier: License :: OSI Approved :: GNU Lesser General Public License v3 or later (LGPLv3+)
Classifier: Natural Language :: English
Classifier: Natural Language :: Spanish
Classifier: Operating System :: OS Independent
Classifier: Programming Language :: Python :: 3.4
Classifier: Programming Language :: Python :: 2.7
Classifier: Topic :: Office/Business
Classifier: Topic :: Printing 
Classifier: Topic :: Text Processing
Requires-Dist: PySide
